fetchpoint/__init__.py
fetchpoint/auth_factory.py
fetchpoint/authenticator.py
fetchpoint/client.py
fetchpoint/config.py
fetchpoint/excel_reader.py
fetchpoint/exceptions.py
fetchpoint/file_handler.py
fetchpoint/models.py
fetchpoint/msal_authenticator.py
fetchpoint/py.typed
fetchpoint/url_utils.py
fetchpoint/diagnostics/__init__.py
fetchpoint/diagnostics/api_tester.py
fetchpoint/diagnostics/cache_inspector.py
fetchpoint/diagnostics/error_classifier.py
fetchpoint/diagnostics/network_validator.py
fetchpoint/diagnostics/permission_analyzer.py
fetchpoint/diagnostics/resource_tester.py
fetchpoint/diagnostics/token_inspector.py
fetchpoint-0.1.1.dist-info/METADATA
fetchpoint-0.1.1.dist-info/WHEEL
fetchpoint-0.1.1.dist-info/licenses/LICENSE
fetchpoint-0.1.1.dist-info/RECORD
