Metadata-Version: 2.4
Name: fetchpoint
Version: 0.1.1
Summary: A modern SharePoint client library for Python with federated authentication support
Project-URL: Homepage, https://github.com/masmau/fetchpoint
Project-URL: Repository, https://github.com/masmau/fetchpoint
Project-URL: Issues, https://github.com/masmau/fetchpoint/issues
Project-URL: Documentation, https://github.com/masmau/fetchpoint#readme
Author: Massimo Mauri
License: MIT
License-File: LICENSE
Keywords: azure-ad,document-management,enterprise,excel,federated-authentication,office365,sharepoint
Classifier: Development Status :: 4 - Beta
Classifier: Intended Audience :: Developers
Classifier: License :: OSI Approved :: MIT License
Classifier: Operating System :: OS Independent
Classifier: Programming Language :: Python :: 3
Classifier: Programming Language :: Python :: 3.10
Classifier: Programming Language :: Python :: 3.11
Classifier: Programming Language :: Python :: 3.12
Classifier: Programming Language :: Python :: 3.13
Classifier: Topic :: Office/Business
Classifier: Topic :: Software Development :: Libraries :: Python Modules
Classifier: Typing :: Typed
Requires-Python: <3.14,>=3.10
Requires-Dist: click>=8.2.1
Requires-Dist: httpx>=0.28.1
Requires-Dist: msal>=1.33.0
Requires-Dist: office365-rest-python-client>=2.6.2
Requires-Dist: openpyxl>=3.1.5
Requires-Dist: pandas>=2.3.0
Requires-Dist: pydantic>=2.11.7
